CHANGELOG.txt
LICENCE.txt
MANIFEST.in
README.txt
setup.py
test.py
ML/__init__.py
ML/automl.py
pysmart_ai.egg-info/PKG-INFO
pysmart_ai.egg-info/SOURCES.txt
pysmart_ai.egg-info/dependency_links.txt
pysmart_ai.egg-info/requires.txt
pysmart_ai.egg-info/top_level.txt